<?xml version="1.0" encoding="UTF-8"?>
<record_update table="sp_css_include">
    <sp_css_include action="INSERT_OR_UPDATE">
        <name>NoSidePadding</name>
        <source>local</source>
        <sp_css display_value="NoSidePadding">2ca04d2d4f11130026f5b3728110c7e5</sp_css>
        <sys_class_name>sp_css_include</sys_class_name>
        <sys_created_by>chris.clayton</sys_created_by>
        <sys_created_on>2018-04-05 22:17:20</sys_created_on>
        <sys_id>34c0c92d4f11130026f5b3728110c786</sys_id>
        <sys_mod_count>0</sys_mod_count>
        <sys_name>NoSidePadding</sys_name>
        <sys_package display_value="Reagents Inventory Management" source="x_195640_reagents">d60be6f34f68130026f5b3728110c73a</sys_package>
        <sys_policy/>
        <sys_scope display_value="Reagents Inventory Management">d60be6f34f68130026f5b3728110c73a</sys_scope>
        <sys_update_name>sp_css_include_34c0c92d4f11130026f5b3728110c786</sys_update_name>
        <sys_updated_by>chris.clayton</sys_updated_by>
        <sys_updated_on>2018-04-05 22:17:20</sys_updated_on>
        <url/>
    </sp_css_include>
</record_update>
